dodcerts/__init__.py
dodcerts/__main__.py
dodcerts/_version.py
dodcerts/bundle.py
dodcerts/cli.py
dodcerts/create.py
dodcerts/dod-ca-certs.pem
dodcerts-1.0.dist-info/LICENSE
dodcerts-1.0.dist-info/METADATA
dodcerts-1.0.dist-info/WHEEL
dodcerts-1.0.dist-info/entry_points.txt
dodcerts-1.0.dist-info/top_level.txt
dodcerts-1.0.dist-info/RECORD
